{
    "name": "level1",
    "dimensions": {
        "width": 12800,
        "height": 576
    },
    "platforms": [
        {
            "start": 0,
            "end": 64,
            "height": 128
        },
        {
            "start": 64,
            "end": 128,
            "height": 128
        },
        {
            "start": 128,
            "end": 192,
            "height": 128
        },
        {
            "start": 192,
            "end": 256,
            "height": 128
        },
        {
            "start": 256,
            "end": 320,
            "height": 128
        },
        {
            "start": 320,
            "end": 384,
            "height": 128
        },
        {
            "start": 384,
            "end": 448,
            "height": 128
        },
        {
            "start": 448,
            "end": 512,
            "height": 128
        },
        {
            "start": 512,
            "end": 576,
            "height": 128
        },
        {
            "start": 576,
            "end": 640,
            "height": 128
        },
        {
            "start": 960,
            "end": 1024,
            "height": 128
        },
        {
            "start": 1024,
            "end": 1088,
            "height": 128
        },
        {
            "start": 1088,
            "end": 1152,
            "height": 128
        },
        {
            "start": 1152,
            "end": 1216,
            "height": 128
        },
        {
            "start": 1216,
            "end": 1280,
            "height": 128
        },
        {
            "start": 1280,
            "end": 1344,
            "height": 128
        },
        {
            "start": 1344,
            "end": 1408,
            "height": 128
        },
        {
            "start": 1408,
            "end": 1472,
            "height": 128
        },
        {
            "start": 1472,
            "end": 1536,
            "height": 128
        },
        {
            "start": 1536,
            "end": 1600,
            "height": 128
        },
        {
            "start": 1600,
            "end": 1664,
            "height": 128
        },
        {
            "start": 1664,
            "end": 1728,
            "height": 128
        },
        {
            "start": 1728,
            "end": 1792,
            "height": 320
        },
        {
            "start": 1792,
            "end": 1856,
            "height": 320
        },
        {
            "start": 1856,
            "end": 1920,
            "height": 320
        },
        {
            "start": 1920,
            "end": 1984,
            "height": 320
        },
        {
            "start": 1984,
            "end": 2048,
            "height": 256
        },
        {
            "start": 2048,
            "end": 2112,
            "height": 256
        },
        {
            "start": 2112,
            "end": 2176,
            "height": 256
        },
        {
            "start": 2176,
            "end": 2240,
            "height": 320
        },
        {
            "start": 2240,
            "end": 2304,
            "height": 320
        },
        {
            "start": 2304,
            "end": 2368,
            "height": 256
        },
        {
            "start": 2496,
            "end": 2560,
            "height": 256
        },
        {
            "start": 2560,
            "end": 2624,
            "height": 320
        },
        {
            "start": 2624,
            "end": 2688,
            "height": 384
        },
        {
            "start": 2688,
            "end": 2752,
            "height": 448
        },
        {
            "start": 2752,
            "end": 2816,
            "height": 512
        },
        {
            "start": 2752,
            "end": 2816,
            "height": 128
        },
        {
            "start": 2816,
            "end": 2880,
            "height": 512
        },
        {
            "start": 2816,
            "end": 2880,
            "height": 128
        },
        {
            "start": 2880,
            "end": 2944,
            "height": 512
        },
        {
            "start": 2880,
            "end": 2944,
            "height": 128
        },
        {
            "start": 2944,
            "end": 3008,
            "height": 512
        },
        {
            "start": 2944,
            "end": 3008,
            "height": 128
        },
        {
            "start": 3008,
            "end": 3072,
            "height": 512
        },
        {
            "start": 3072,
            "end": 3136,
            "height": 512
        },
        {
            "start": 3136,
            "end": 3200,
            "height": 512
        },
        {
            "start": 3200,
            "end": 3264,
            "height": 512
        },
        {
            "start": 3200,
            "end": 3264,
            "height": 320
        },
        {
            "start": 3264,
            "end": 3328,
            "height": 512
        },
        {
            "start": 3264,
            "end": 3328,
            "height": 320
        },
        {
            "start": 3328,
            "end": 3392,
            "height": 512
        },
        {
            "start": 3328,
            "end": 3392,
            "height": 320
        },
        {
            "start": 3392,
            "end": 3456,
            "height": 320
        },
        {
            "start": 3456,
            "end": 3520,
            "height": 320
        },
        {
            "start": 3968,
            "end": 4032,
            "height": 192
        },
        {
            "start": 4032,
            "end": 4096,
            "height": 192
        },
        {
            "start": 4096,
            "end": 4160,
            "height": 192
        },
        {
            "start": 4160,
            "end": 4224,
            "height": 192
        },
        {
            "start": 4224,
            "end": 4288,
            "height": 192
        },
        {
            "start": 4288,
            "end": 4352,
            "height": 192
        },
        {
            "start": 4352,
            "end": 4416,
            "height": 192
        },
        {
            "start": 4416,
            "end": 4480,
            "height": 192
        },
        {
            "start": 4480,
            "end": 4544,
            "height": 192
        },
        {
            "start": 4544,
            "end": 4608,
            "height": 192
        },
        {
            "start": 4608,
            "end": 4672,
            "height": 192
        },
        {
            "start": 4672,
            "end": 4736,
            "height": 192
        },
        {
            "start": 4736,
            "end": 4800,
            "height": 192
        },
        {
            "start": 4800,
            "end": 4864,
            "height": 192
        },
        {
            "start": 4864,
            "end": 4928,
            "height": 192
        },
        {
            "start": 4928,
            "end": 4992,
            "height": 192
        },
        {
            "start": 4992,
            "end": 5056,
            "height": 192
        },
        {
            "start": 5056,
            "end": 5120,
            "height": 192
        },
        {
            "start": 5120,
            "end": 5184,
            "height": 192
        },
        {
            "start": 5184,
            "end": 5248,
            "height": 192
        }
    ],
    "startingPosition": {
        "x": 64,
        "y": 512
    }
}
